README.md
setup.py
dataperm/__init__.py
dataperm/admin.py
dataperm/apps.py
dataperm/models.py
dataperm/tests.py
dataperm/views.py
dataperm/migrations/__init__.py
demotst/migrations/0001_initial.py
demotst/migrations/__init__.py
django_dataperm_model.egg-info/PKG-INFO
django_dataperm_model.egg-info/SOURCES.txt
django_dataperm_model.egg-info/dependency_links.txt
django_dataperm_model.egg-info/requires.txt
django_dataperm_model.egg-info/top_level.txt